odoo8_addon_sale_order_line_variant_description-8.0.1.0.0.99.dev20-py3.8-nspkg.pth
odoo_addons/sale_order_line_variant_description/README.rst
odoo_addons/sale_order_line_variant_description/__init__.py
odoo_addons/sale_order_line_variant_description/__openerp__.py
odoo_addons/sale_order_line_variant_description/i18n/ca.po
odoo_addons/sale_order_line_variant_description/i18n/de.po
odoo_addons/sale_order_line_variant_description/i18n/el_GR.po
odoo_addons/sale_order_line_variant_description/i18n/es.po
odoo_addons/sale_order_line_variant_description/i18n/es_ES.po
odoo_addons/sale_order_line_variant_description/i18n/fi.po
odoo_addons/sale_order_line_variant_description/i18n/fr.po
odoo_addons/sale_order_line_variant_description/i18n/fr_CH.po
odoo_addons/sale_order_line_variant_description/i18n/fr_FR.po
odoo_addons/sale_order_line_variant_description/i18n/gl.po
odoo_addons/sale_order_line_variant_description/i18n/hr.po
odoo_addons/sale_order_line_variant_description/i18n/hr_HR.po
odoo_addons/sale_order_line_variant_description/i18n/it.po
odoo_addons/sale_order_line_variant_description/i18n/nl.po
odoo_addons/sale_order_line_variant_description/i18n/nl_NL.po
odoo_addons/sale_order_line_variant_description/i18n/pt.po
odoo_addons/sale_order_line_variant_description/i18n/pt_BR.po
odoo_addons/sale_order_line_variant_description/i18n/ro.po
odoo_addons/sale_order_line_variant_description/i18n/ru.po
odoo_addons/sale_order_line_variant_description/i18n/sale_order_line_variant_description.pot
odoo_addons/sale_order_line_variant_description/i18n/sk.po
odoo_addons/sale_order_line_variant_description/i18n/sl.po
odoo_addons/sale_order_line_variant_description/i18n/tr.po
odoo_addons/sale_order_line_variant_description/i18n/tr_TR.po
odoo_addons/sale_order_line_variant_description/i18n/vi_VN.po
odoo_addons/sale_order_line_variant_description/i18n/zh_CN.po
odoo_addons/sale_order_line_variant_description/models/__init__.py
odoo8_addon_sale_order_line_variant_description-8.0.1.0.0.99.dev20.dist-info/METADATA
odoo8_addon_sale_order_line_variant_description-8.0.1.0.0.99.dev20.dist-info/WHEEL
odoo8_addon_sale_order_line_variant_description-8.0.1.0.0.99.dev20.dist-info/namespace_packages.txt
odoo8_addon_sale_order_line_variant_description-8.0.1.0.0.99.dev20.dist-info/top_level.txt
odoo8_addon_sale_order_line_variant_description-8.0.1.0.0.99.dev20.dist-info/RECORD
